mlignore/__init__.py
mlignore/main.py
mlignore-0.1.0.dist-info/WHEEL
mlignore-0.1.0.dist-info/entry_points.txt
mlignore-0.1.0.dist-info/METADATA
mlignore-0.1.0.dist-info/RECORD
