Metadata-Version: 2.3
Name: mlignore
Version: 0.1.0
Summary: mlignore: The Industrial-Grade Context Leakage Utility. Optimized for feeding LLMs minified codebase contexts. 
Requires-Dist: pathspec>=0.12.1
Requires-Dist: tree-sitter>=0.25.2
Requires-Dist: tree-sitter-css>=0.25.0
Requires-Dist: tree-sitter-javascript>=0.25.0
Requires-Dist: tree-sitter-python>=0.25.0
Requires-Dist: typer>=0.21.0
Requires-Python: >=3.12
